{
  "sections": {
    "main": {
      "type": "main-page",
      "disabled": true,
      "settings": {
        "show_title": true,
        "page_width": "medium"
      }
    },
    "1659521461c87c726c": {
      "type": "image-with-text-overlay",
      "settings": {
        "reveal_on_scroll": true,
        "section_height": "medium",
        "image": "shopify:\/\/shop_images\/wandermut-abenteuer-blog-titel.jpg",
        "subheading": "",
        "title": "JOBS",
        "content": "",
        "button_text": "",
        "button_link": "",
        "link_style": "link",
        "background_type": "full_width",
        "text_width": "medium",
        "text_position": "middle_center",
        "text_color": "#ffffff",
        "button_background": "#ffffff",
        "button_text_color": "#000000",
        "overlay_color": "#000000",
        "overlay_opacity": 30
      }
    },
    "1659875722b589956c": {
      "type": "rich-text",
      "disabled": true,
      "settings": {
        "subheading": "",
        "title": "UNSERE VISION: MEHR ABENTEUER!",
        "content": "<p>Wir wollen menschen dazu inspirieren die Natur zu genießen und die Abenteuer zu erleben, von denen sie schon immer geträumt haben. Deshalb planen wir extreme Abenteuer & Expeditionen, und entwickeln Outdoor Bekleidung, um uns bestens ausgestattet ins nächste Abenteuer zu stürzen.<\/p>",
        "button_text": "",
        "button_link": "",
        "background_type": "full_width",
        "text_width": "medium",
        "text_position": "center",
        "text_alignment": "center",
        "background": "#030000",
        "text_color": "#ffffff",
        "button_background": "rgba(0,0,0,0)",
        "button_text_color": "rgba(0,0,0,0)"
      }
    },
    "165987713916c6dc99": {
      "type": "image-with-text-overlay",
      "settings": {
        "reveal_on_scroll": true,
        "section_height": "small",
        "image": "shopify:\/\/shop_images\/DSCF3893-scaled.jpg",
        "subheading": "",
        "title": "UNSERE VISION: MEHR ABENTEUER!",
        "content": "<p>Wir wollen menschen dazu inspirieren die Natur zu genießen und die Abenteuer zu erleben, von denen sie schon immer geträumt haben. Deshalb planen wir extreme Abenteuer & Expeditionen, und entwickeln Outdoor Bekleidung, um uns bestens ausgestattet ins nächste Abenteuer zu stürzen.<\/p>",
        "button_text": "",
        "button_link": "",
        "link_style": "link",
        "background_type": "full_width",
        "text_width": "medium",
        "text_position": "middle_center",
        "text_color": "#030000",
        "button_background": "#ffffff",
        "button_text_color": "#000000",
        "overlay_color": "#ffffff",
        "overlay_opacity": 90
      }
    },
    "1659521508636c46fd": {
      "type": "image-with-text",
      "disabled": true,
      "blocks": {
        "1659521508a3c4caea-0": {
          "type": "item",
          "settings": {
            "image": "shopify:\/\/shop_images\/Vision-9.0.jpg",
            "tab_label": "Item",
            "subheading": "",
            "title": "UNSERE VISION: MEHR ABENTEUER!",
            "content": "<p>Wir haben schon so viele Abenteuer erlebt, sei es mit Husky-Schlitten durch den bitterkalten russischen Winter zu fahren, Ruinen im dichten Regenwald des Amazonas zu finden oder mit einer Dromedar-Karawane über 200 Km durch die Sahara zu ziehen – immer auf der Suche nach der nächsten Oase.<\/p><p>Aber das reicht uns nicht. Nicht einmal im Ansatz.<\/p><p>Es gibt noch so viel mehr. Wir haben Bock die größten Abenteuer-Legenden unserer Zeit kennenzulernen, uns auf einer einsamen Insel aussetzen zu lassen, ein Wandermut-Clubhouse aufzubauen, eine deutschlandweite Wanderung anzuführen, ein gigantisches Sommerfest auf einer Burg für alle Abenteurer auszurichten, einen Goldschatz zu vergraben und selbst nach einem Goldschatz suchen, einmal bei der EOFT dabei zu sein oder gar eine eigene Netflix-Serie zu haben, indigene Sprachen vor dem Aussterben Retten, das größte Naturschutzgebiet im Amazonas zu errichten oder mit einem alten Dreimaster in die Südsee aufbrechen. Glaub uns, wir haben noch mehr Ideen!<\/p><p>Könntest du dir vorstellen, einmal mit der ganzen Community eine Insel in der Karibik zu crowdfunden? Ja? Wir auch! Klingt verrückt und das ist es auch. Aber wir feiern es. Du auch?<\/p>",
            "button_text": "",
            "button_link": ""
          }
        }
      },
      "block_order": [
        "1659521508a3c4caea-0"
      ],
      "settings": {
        "reveal_on_scroll": true,
        "background_color": "#000000",
        "background_type": "full_width",
        "background_overlap": "image",
        "image_position": "right",
        "text_alignment": "center",
        "cycle_speed": 8,
        "accent_background": "rgba(0,0,0,0)",
        "text_color": "#ffffff",
        "button_background": "rgba(0,0,0,0)",
        "button_text_color": "rgba(0,0,0,0)",
        "background_section_color": "#ffffff"
      }
    },
    "1659875940108308bd": {
      "type": "rich-text",
      "disabled": true,
      "settings": {
        "subheading": "",
        "title": "DEINE MISSION",
        "content": "<p>Du stehst auch nicht auf Massen- und Pauschaltourismus oder diese spießigen Regenjacken für alte Leute mit der gelben Tatze auf der Brust? Dann lass uns gemeinsam das Wandern und Reisen wieder cool machen! Wir freuen uns auf deine Bewerbung und darauf, dich vielleicht schon bald im Team Wandermut begrüßen zu dürfen.<\/p><p><\/p><p><em>PS.: Um zu beweisen, dass du bei uns richtig bist, wirst du dich schon bald selbst in einem Abenteuer behaupten müssen. – Bist du dabei? <\/em><\/p>",
        "button_text": "",
        "button_link": "",
        "background_type": "full_width",
        "text_width": "large",
        "text_position": "center",
        "text_alignment": "center",
        "background": "#030000",
        "text_color": "#ffffff",
        "button_background": "rgba(0,0,0,0)",
        "button_text_color": "rgba(0,0,0,0)"
      }
    },
    "1659876801b90fb59d": {
      "type": "rich-text",
      "settings": {
        "subheading": "",
        "title": "UNSERE WERTE",
        "content": "",
        "button_text": "",
        "button_link": "",
        "background_type": "full_width",
        "text_width": "medium",
        "text_position": "center",
        "text_alignment": "center",
        "background": "#030000",
        "text_color": "#ffffff",
        "button_background": "rgba(0,0,0,0)",
        "button_text_color": "rgba(0,0,0,0)"
      }
    },
    "1659876773cbc1b8c5": {
      "type": "text-with-icons",
      "blocks": {
        "16598767733590374b-0": {
          "type": "item",
          "settings": {
            "icon": "picto-box",
            "custom_icon": "shopify:\/\/shop_images\/wandermut-Icon-Zelt.png",
            "custom_icon_width": 50,
            "title": "WIR BRENNEN FÜR ECHTE ABENTEUER!",
            "content": "<p>Wir stehen auf Abenteuer und Ausrüstung, auf die man sich verlassen kann.<\/p>"
          }
        },
        "16598767733590374b-1": {
          "type": "item",
          "settings": {
            "icon": "picto-phone",
            "custom_icon": "shopify:\/\/shop_images\/wandermut-Icon-Wegweiser.png",
            "custom_icon_width": 50,
            "title": "WIR FRAGEN UNS NICHT OB, SONDERN WIE",
            "content": "<p>Wir sehen Lösungen, statt Probleme  und machen so das Undenkbare möglich.<\/p>"
          }
        },
        "16598767733590374b-2": {
          "type": "item",
          "settings": {
            "icon": "picto-lock",
            "custom_icon": "shopify:\/\/shop_images\/muscle-icon-10-small.png",
            "custom_icon_width": 50,
            "title": "WIR HABEN HOHE ANSPRÜCHE",
            "content": "<p>An unser Equipment, an unsere Teilnehmer, und vor allem an uns selbst.<\/p>"
          }
        },
        "16598767733590374b-3": {
          "type": "item",
          "settings": {
            "icon": "picto-email",
            "custom_icon": "shopify:\/\/shop_images\/conversation_icdon_white.png",
            "custom_icon_width": 50,
            "title": "WIR HABEN EINE COMMUNITY, KEINE KUNDEN.",
            "content": "<p>Wandermut ist von Abenteurern, für Abenteurer.<\/p>"
          }
        }
      },
      "block_order": [
        "16598767733590374b-0",
        "16598767733590374b-1",
        "16598767733590374b-2",
        "16598767733590374b-3"
      ],
      "settings": {
        "background": "#030000",
        "text_color": "#ffffff"
      }
    },
    "1659877298bd791947": {
      "type": "image-with-text-overlay",
      "settings": {
        "reveal_on_scroll": true,
        "section_height": "small",
        "image": "shopify:\/\/shop_images\/DJI_0091-scaled.jpg",
        "subheading": "",
        "title": "Bist du einer von uns?",
        "content": "<p>Du stehst auch nicht auf Massen- und Pauschaltourismus oder diese spießigen Regenjacken für alte Leute mit der gelben Tatze auf der Brust? Dann lass uns gemeinsam das Wandern und Reisen wieder cool machen! Wir freuen uns auf deine Bewerbung und darauf, dich vielleicht schon bald im Team Wandermut begrüßen zu dürfen.<\/p><p><\/p><p><em>PS.: Um zu beweisen, dass du bei uns richtig bist, wirst du dich schon bald selbst in einem Abenteuer behaupten müssen. – Bist du dabei? <\/em><\/p>",
        "button_text": "",
        "button_link": "",
        "link_style": "link",
        "background_type": "full_width",
        "text_width": "medium",
        "text_position": "middle_center",
        "text_color": "#030000",
        "button_background": "#ffffff",
        "button_text_color": "#000000",
        "overlay_color": "#ffffff",
        "overlay_opacity": 80
      }
    },
    "165987829626066190": {
      "type": "multi-column",
      "disabled": true,
      "blocks": {
        "1659878296419a52ef-0": {
          "type": "item",
          "settings": {
            "image": "shopify:\/\/shop_images\/wandermut-Icon-Zelt.png",
            "image_width": 20,
            "image_border": "rgba(0,0,0,0)",
            "title": "WIR BRENNEN FÜR ECHTE ABENTEUER!",
            "content": "<p>Wir stehen auf Abenteuer und Ausrüstung, auf die man sich verlassen kann.<\/p>",
            "link_text": "",
            "link_url": "",
            "link_style": "link",
            "text_alignment": "center",
            "vertical_alignment": "start"
          }
        },
        "1659878296419a52ef-1": {
          "type": "item",
          "settings": {
            "image": "shopify:\/\/shop_images\/wandermut-Icon-Wegweiser.png",
            "image_width": 20,
            "image_border": "rgba(0,0,0,0)",
            "title": "WIR FRAGEN UNS NICHT OB, SONDERN WIE",
            "content": "<p>Wir sehen Lösungen, statt Probleme  und machen dadurch das undenkbare möglich.<\/p>",
            "link_text": "",
            "link_url": "",
            "link_style": "link",
            "text_alignment": "center",
            "vertical_alignment": "start"
          }
        },
        "1659878296419a52ef-2": {
          "type": "item",
          "settings": {
            "image": "shopify:\/\/shop_images\/muscle-icon-10-white_2b93bdc5-d76d-4f11-8189-14c0e694681b.png",
            "image_width": 20,
            "image_border": "rgba(0,0,0,0)",
            "title": "WIR HABEN HOHE ANSPRÜCHE",
            "content": "<p>An unser Equipment, an unsere Teilnehmer, und vor allem an uns selbst.<\/p>",
            "link_text": "",
            "link_url": "",
            "link_style": "link",
            "text_alignment": "center",
            "vertical_alignment": "start"
          }
        },
        "1659878296419a52ef-3": {
          "type": "item",
          "settings": {
            "image": "shopify:\/\/shop_images\/conversation_icdon_white.png",
            "image_width": 21,
            "image_border": "rgba(0,0,0,0)",
            "title": "WIR HABEN EINE COMMUNITY, KEINE KUNDEN.",
            "content": "<p>Wandermut ist von Abenteurern, für Abenteurer.<\/p>",
            "link_text": "",
            "link_url": "",
            "link_style": "link",
            "text_alignment": "center",
            "vertical_alignment": "start"
          }
        }
      },
      "block_order": [
        "1659878296419a52ef-0",
        "1659878296419a52ef-1",
        "1659878296419a52ef-2",
        "1659878296419a52ef-3"
      ],
      "settings": {
        "reveal_on_scroll": true,
        "stack_items": false,
        "subheading": "Subheading",
        "title": "Multi-column",
        "content": "",
        "column_alignment": "center",
        "mobile_item_size": "medium",
        "desktop_item_size": "medium",
        "spacing": "normal",
        "background": "#030000",
        "text_color": "#ffffff"
      }
    },
    "165952190532ba611e": {
      "type": "multi-column",
      "blocks": {
        "16595219057321024f-0": {
          "type": "item",
          "settings": {
            "image": "shopify:\/\/shop_images\/Social-Media.jpg",
            "image_width": 100,
            "image_border": "rgba(0,0,0,0)",
            "title": "Performance Marketing (m\/w\/d)",
            "content": "",
            "link_text": "ZUR BEWERBUNG",
            "link_url": "shopify:\/\/pages\/benteuer-performance-marketing-manag",
            "link_style": "link",
            "text_alignment": "center",
            "vertical_alignment": "start"
          }
        },
        "16595219057321024f-1": {
          "type": "item",
          "settings": {
            "image": "shopify:\/\/shop_images\/IMG_1370-scaled.jpg",
            "image_width": 100,
            "image_border": "rgba(0,0,0,0)",
            "title": "Social media manager (m\/w\/d)",
            "content": "",
            "link_text": "ZUR BEWERBUNG",
            "link_url": "shopify:\/\/pages\/abenteuer-social-media-manager",
            "link_style": "link",
            "text_alignment": "center",
            "vertical_alignment": "start"
          }
        },
        "16595219057321024f-2": {
          "type": "item",
          "settings": {
            "image": "shopify:\/\/shop_images\/Auf-Pferden-durch-die-Monolei-37.jpg",
            "image_width": 100,
            "image_border": "rgba(0,0,0,0)",
            "title": "online marketing manager (m\/w\/d)",
            "content": "",
            "link_text": "ZUR BEWERBUNG",
            "link_url": "shopify:\/\/pages\/online-marketing-manage",
            "link_style": "link",
            "text_alignment": "center",
            "vertical_alignment": "start"
          }
        },
        "16595219057321024f-3": {
          "type": "item",
          "settings": {
            "image": "shopify:\/\/shop_images\/Sahara-2017-Doku-0129-scaled.jpg",
            "image_width": 100,
            "image_border": "rgba(0,0,0,0)",
            "title": "content creator (m\/w\/d)",
            "content": "",
            "link_text": "ZUR BEWERBUNG",
            "link_url": "shopify:\/\/pages\/content-creator",
            "link_style": "link",
            "text_alignment": "center",
            "vertical_alignment": "start"
          }
        },
        "8ac2b1f6-e24e-404f-84a2-61ee81762388": {
          "type": "item",
          "settings": {
            "image": "shopify:\/\/shop_images\/P1060761.jpg",
            "image_width": 100,
            "image_border": "rgba(0,0,0,0)",
            "title": "influencer relations manager (m\/w\/d)",
            "content": "",
            "link_text": "ZUR BEWERBUNG",
            "link_url": "shopify:\/\/pages\/influencer-relations-manager",
            "link_style": "link",
            "text_alignment": "center",
            "vertical_alignment": "start"
          }
        },
        "790a9687-0e2f-4285-89bb-55911ee98c1a": {
          "type": "item",
          "settings": {
            "image": "shopify:\/\/shop_images\/Design-ohne-Titel-2.jpg",
            "image_width": 100,
            "image_border": "rgba(0,0,0,0)",
            "title": "produkt manager apparel(m\/w\/d)",
            "content": "",
            "link_text": "ZUR BEWERBUNG",
            "link_url": "shopify:\/\/pages\/abenteuer-produkt-manager",
            "link_style": "link",
            "text_alignment": "center",
            "vertical_alignment": "start"
          }
        },
        "42f70c95-24c5-472f-ad7a-44b21e31646b": {
          "type": "item",
          "settings": {
            "image": "shopify:\/\/shop_images\/Sahara-2017-Doku-0948-scaled.jpg",
            "image_width": 100,
            "image_border": "rgba(0,0,0,0)",
            "title": "produktentwickler und designer textil (m\/w\/d)",
            "content": "",
            "link_text": "ZUR BEWERBUNG",
            "link_url": "shopify:\/\/pages\/produktentwickler-designer-textil",
            "link_style": "link",
            "text_alignment": "center",
            "vertical_alignment": "start"
          }
        },
        "60874c7a-4846-431d-b206-62e2d975a1a4": {
          "type": "item",
          "settings": {
            "image": "shopify:\/\/shop_images\/Husky_Expedition_Kostroma_2017_755-scaled.jpg",
            "image_width": 100,
            "image_border": "rgba(0,0,0,0)",
            "title": "Abenteurer Tourenplaner & Manager (m\/w\/d)",
            "content": "",
            "link_text": "ZUR BEWERBUNG",
            "link_url": "shopify:\/\/pages\/abenteurer-tourenplaner-manager",
            "link_style": "link",
            "text_alignment": "center",
            "vertical_alignment": "start"
          }
        },
        "2c0c49b6-ca3f-40f0-953d-82a36d91e2fb": {
          "type": "item",
          "settings": {
            "image": "shopify:\/\/shop_images\/Thomas-IMG_1545.jpg",
            "image_width": 100,
            "image_border": "rgba(0,0,0,0)",
            "title": "Assistenz der Geschäftsführung (m\/w\/d)",
            "content": "",
            "link_text": "ZUR BEWERBUNG",
            "link_url": "shopify:\/\/pages\/assistenz-der-geschaftsfuhrung",
            "link_style": "link",
            "text_alignment": "center",
            "vertical_alignment": "start"
          }
        },
        "79a8549d-e3cd-45d3-a625-bb441fa95c30": {
          "type": "item",
          "settings": {
            "image": "shopify:\/\/shop_images\/Wandermut-Sahara-2018-71-scaled.jpg",
            "image_width": 100,
            "image_border": "rgba(0,0,0,0)",
            "title": "Business Developer \/ Berater(m\/w\/d)",
            "content": "",
            "link_text": "ZUR BEWERBUNG",
            "link_url": "shopify:\/\/pages\/business-developer-berater",
            "link_style": "link",
            "text_alignment": "center",
            "vertical_alignment": "start"
          }
        },
        "e55511cf-2a85-4bdd-b05c-2fa5a16052c8": {
          "type": "item",
          "settings": {
            "image": "shopify:\/\/shop_images\/Chachapoya-Expedition-2018-733-2.jpg",
            "image_width": 100,
            "image_border": "rgba(0,0,0,0)",
            "title": "Werkstudent: Produktmanagement \/ Abentuer-Planung (m\/w\/d)",
            "content": "",
            "link_text": "ZUR BEWERBUNG",
            "link_url": "shopify:\/\/pages\/werkstudent-fur-abenteuer-marketing",
            "link_style": "link",
            "text_alignment": "center",
            "vertical_alignment": "start"
          }
        },
        "dd6e6a8d-b648-4fc5-ab77-0a74262d2ea5": {
          "type": "item",
          "settings": {
            "image": "shopify:\/\/shop_images\/Simon-DSC_1818-scaled.jpg",
            "image_width": 100,
            "image_border": "rgba(0,0,0,0)",
            "title": "Werkstudent: Produktmanagement (m\/w\/d)",
            "content": "",
            "link_text": "ZUR BEWERBUNG",
            "link_url": "shopify:\/\/pages\/werkstudent-fur-das-produktmanagement",
            "link_style": "link",
            "text_alignment": "center",
            "vertical_alignment": "start"
          }
        },
        "1eb53412-1c01-4740-90b0-fb98b627574b": {
          "type": "item",
          "settings": {
            "image": "shopify:\/\/shop_images\/Sahara-2017-Doku-0923-scaled.jpg",
            "image_width": 100,
            "image_border": "rgba(0,0,0,0)",
            "title": "Werkstudent für Marketing & Social Media (m\/w\/d)",
            "content": "",
            "link_text": "ZUR BEWERBUNG",
            "link_url": "shopify:\/\/pages\/werkstudent-projektmanagement",
            "link_style": "link",
            "text_alignment": "center",
            "vertical_alignment": "start"
          }
        },
        "0242a99c-beaa-415d-bd43-c5e67117e9dc": {
          "type": "item",
          "settings": {
            "image": "shopify:\/\/shop_images\/Wandermut-Sahara-Tour-7.jpg",
            "image_width": 100,
            "image_border": "rgba(0,0,0,0)",
            "title": "Teamleiter (m\/w\/d)",
            "content": "",
            "link_text": "ZUR BEWERBUNG",
            "link_url": "shopify:\/\/pages\/teamleiter",
            "link_style": "link",
            "text_alignment": "center",
            "vertical_alignment": "start"
          }
        }
      },
      "block_order": [
        "16595219057321024f-0",
        "16595219057321024f-1",
        "16595219057321024f-2",
        "16595219057321024f-3",
        "8ac2b1f6-e24e-404f-84a2-61ee81762388",
        "790a9687-0e2f-4285-89bb-55911ee98c1a",
        "42f70c95-24c5-472f-ad7a-44b21e31646b",
        "60874c7a-4846-431d-b206-62e2d975a1a4",
        "2c0c49b6-ca3f-40f0-953d-82a36d91e2fb",
        "79a8549d-e3cd-45d3-a625-bb441fa95c30",
        "e55511cf-2a85-4bdd-b05c-2fa5a16052c8",
        "dd6e6a8d-b648-4fc5-ab77-0a74262d2ea5",
        "1eb53412-1c01-4740-90b0-fb98b627574b",
        "0242a99c-beaa-415d-bd43-c5e67117e9dc"
      ],
      "settings": {
        "reveal_on_scroll": true,
        "stack_items": true,
        "subheading": "Festangestellte müssen einmal mit uns durch die Sahara - bist du dabei?",
        "title": "AKTUELLE JOBS BEI WANDERMUT",
        "content": "",
        "column_alignment": "center",
        "mobile_item_size": "large",
        "desktop_item_size": "large",
        "spacing": "normal",
        "background": "#2e2e2e",
        "text_color": "#ffffff"
      }
    },
    "1659522707bd228f53": {
      "type": "image-with-text-overlay",
      "settings": {
        "reveal_on_scroll": true,
        "section_height": "medium",
        "image": "shopify:\/\/shop_images\/Screenshot_2022-07-06_082109.png",
        "subheading": "",
        "title": "UNSER OFFICE",
        "content": "<p>Direkt in der Kölner Innenstadt.<\/p>",
        "button_text": "",
        "button_link": "",
        "link_style": "link",
        "background_type": "full_width",
        "text_width": "medium",
        "text_position": "middle_center",
        "text_color": "#ffffff",
        "button_background": "#ffffff",
        "button_text_color": "#000000",
        "overlay_color": "#000000",
        "overlay_opacity": 15
      }
    },
    "16595228026a62c93f": {
      "type": "video",
      "settings": {
        "subheading": "",
        "title": "WIR SIND WANDERMUT",
        "video_url": "https:\/\/www.youtube.com\/watch?v=w1rQfmPirQE",
        "background_type": "boxed",
        "video_size": "small",
        "autoplay": true,
        "background": "#000000",
        "text_color": "#ffffff"
      }
    }
  },
  "order": [
    "main",
    "1659521461c87c726c",
    "1659875722b589956c",
    "165987713916c6dc99",
    "1659521508636c46fd",
    "1659875940108308bd",
    "1659876801b90fb59d",
    "1659876773cbc1b8c5",
    "1659877298bd791947",
    "165987829626066190",
    "165952190532ba611e",
    "1659522707bd228f53",
    "16595228026a62c93f"
  ]
}